meta_features/__init__.py
meta_features/__version__.py
meta_features-0.0.1.dist-info/LICENSE
meta_features-0.0.1.dist-info/METADATA
meta_features-0.0.1.dist-info/WHEEL
meta_features-0.0.1.dist-info/top_level.txt
meta_features-0.0.1.dist-info/RECORD
