Metadata-Version: 2.1
Name: meta-features
Version: 0.0.1
Summary: A python package for metalearning.
Home-page: https://github.com/mkumar73/meta-features
Author: Manish Kumar
Author-email: manishkr7003@gmail.com
License: Copyright (c) Manish Kumar 2024 
Project-URL: Documentation, https://meta_features.readthedocs.io/en/
Platform: UNKNOWN
Classifier: Programming Language :: Python :: 3
Classifier: License :: OSI Approved :: MIT License
Classifier: Operating System :: OS Independent
Requires-Python: >=3.8, <=3.12.3
Requires-Dist: numpy<=1.26.4
Requires-Dist: pandas
Requires-Dist: scikit-learn
Requires-Dist: setuptools
